pykallisto/__init__.py
pykallisto/methods.py
pykallisto/pykallisto.py
pykallisto-0.0.5.dist-info/METADATA
pykallisto-0.0.5.dist-info/WHEEL
pykallisto-0.0.5.dist-info/top_level.txt
pykallisto-0.0.5.dist-info/RECORD
