Metadata-Version: 2.1
Name: pykallisto
Version: 0.0.5
Summary: A small library for taking the transpose of arbitrarily large .csvs
Home-page: https://github.com/jlehrer1/pykallisto
Author: Julian Lehrer
Author-email: jmlehrer@ucsc.edu
License: MIT license
Keywords: pykallisto
Platform: UNKNOWN
Classifier: Development Status :: 3 - Alpha
Classifier: Intended Audience :: Developers
Classifier: License :: OSI Approved :: GNU General Public License v2 (GPLv2)
Classifier: Natural Language :: English
Classifier: Programming Language :: Python :: 3
Classifier: Programming Language :: Python :: 3.6
Classifier: Programming Language :: Python :: 3.7
Classifier: Programming Language :: Python :: 3.8
Requires-Python: >=3.6
Requires-Dist: pandas
Requires-Dist: numpy
Requires-Dist: tqdm
Requires-Dist: boto3
